acceptance/__init__.py
acceptance/client_test.py
py_nextbus/__init__.py
py_nextbus/client.py
py_nextbus/models.py
py_nextbusnext-2.3.0.dist-info/licenses/LICENSE
py_nextbusnext-2.3.0.dist-info/METADATA
py_nextbusnext-2.3.0.dist-info/WHEEL
py_nextbusnext-2.3.0.dist-info/top_level.txt
py_nextbusnext-2.3.0.dist-info/RECORD
